README.md
setup.py
cmscraper/__init__.py
cmscraper/cmscraper_cli.py
cmscraper/scraper.py
cmscraper/devices/__init__.py
cmscraper/devices/technicolor/__init__.py
cmscraper/devices/technicolor/dpc3848ve.py
cmscraper/devices/technicolor/test_dpc3848ve.py
cmstats/__init__.py
cmstats/cmstats_cli.py
cmstool.egg-info/PKG-INFO
cmstool.egg-info/SOURCES.txt
cmstool.egg-info/dependency_links.txt
cmstool.egg-info/entry_points.txt
cmstool.egg-info/requires.txt
cmstool.egg-info/top_level.txt