Metadata-Version: 1.0
Name: cmstool
Version: 0.1b0
Summary: Cable Modem Statistics Tool
Home-page: https://github.com/charlysan/cmstool/
Author: charlysan
Author-email: chrlysn0@gmail.com
License: MIT
Platform: UNKNOWN
